dian_utils/__init__.py
dian_utils/verifier.py
dian_utils-1.0.0.dist-info/licenses/LICENSE
dian_utils-1.0.0.dist-info/METADATA
dian_utils-1.0.0.dist-info/WHEEL
dian_utils-1.0.0.dist-info/top_level.txt
dian_utils-1.0.0.dist-info/RECORD
