Metadata-Version: 2.4
Name: dian-utils
Version: 1.0.0
Summary: Validador de NIT colombiano con detección de patrones sospechosos
Author: Juan Perea
License: MIT License
Project-URL: Homepage, https://github.com/jdperea/dian-utils
Requires-Python: >=3.7
License-File: LICENSE
Dynamic: license-file
